badai/__init__.py
badai/_nbdev.py
badai/utils.py
badai/vision/__init__.py
badai/vision/core.py
badai-0.0.8.dist-info/DESCRIPTION.rst
badai-0.0.8.dist-info/METADATA
badai-0.0.8.dist-info/RECORD
badai-0.0.8.dist-info/WHEEL
badai-0.0.8.dist-info/entry_points.txt
badai-0.0.8.dist-info/metadata.json
badai-0.0.8.dist-info/top_level.txt
