Metadata-Version: 2.0
Name: badai
Version: 0.0.8
Summary: No idea what Im doing. Might be useful
Home-page: https://github.com/pattyhendrix/badai
Author: pattyhendrix
Author-email: jpatnick10@gmail.com
License: Apache Software License 2.0
Keywords: badai deep learning machine learning
Platform: UNKNOWN
Classifier: Development Status :: 3 - Alpha
Classifier: Intended Audience :: Developers
Classifier: License :: OSI Approved :: Apache Software License
Classifier: Natural Language :: English
Classifier: Programming Language :: Python :: 3.6
Classifier: Programming Language :: Python :: 3.7
Classifier: Programming Language :: Python :: 3.8
Requires-Python: >=3.6
Requires-Dist: ppretty
Requires-Dist: colorama
